{
    "border": {
        "type": "dimension",
        "radius": {
            "circle": {
                "value": "999999rem"
            },
            "extra-small": {
                "value": "0.25rem"
            },
            "small": {
                "value": "0.5rem"
            },
            "medium": {
                "value": "0.75rem"
            },
            "large": {
                "value": "1rem"
            },
            "exra-large": {
                "value": "1.75rem"
            }
        },
        "width": {
            "0": {
                "value": "0px"
            },
            "small": {
                "value": "1px"
            },
            "medium": {
                "value": "2px"
            },
            "large": {
                "value": "4px"
            }
        }
    }
}
